sentinel_datetime.py
sentinel_datetime-0.0.4.dist-info/METADATA
sentinel_datetime-0.0.4.dist-info/WHEEL
sentinel_datetime-0.0.4.dist-info/top_level.txt
sentinel_datetime-0.0.4.dist-info/RECORD
