Metadata-Version: 2.1
Name: sentinel-datetime
Version: 0.0.4
Summary: Sentinel Result Object for python-dateutil
Home-page: UNKNOWN
Author: S. Williams-Wynn
Author-email: s.williamswynn.mail@gmail.com
License: UNKNOWN
Platform: UNKNOWN
Requires-Python: >=3.6
Requires-Dist: python-dateutil
